Optionchain/__init__.py
optiondata_ab-0.1.dist-info/LICENSE.txt
optiondata_ab-0.1.dist-info/METADATA
optiondata_ab-0.1.dist-info/WHEEL
optiondata_ab-0.1.dist-info/top_level.txt
optiondata_ab-0.1.dist-info/RECORD
