Metadata-Version: 2.1
Name: optiondata-ab
Version: 0.1
Summary: aliceblue_onlyoption
Author: nanda
Author-email: nandagopalherballife@gmail.com
Classifier: Programming Language :: Python :: 3
Classifier: License :: OSI Approved :: MIT License
Classifier: Operating System :: OS Independent
License-File: LICENSE.txt
